azure/ai/agentserver/__init__.py
azure/ai/agentserver/agentframework/__init__.py
azure/ai/agentserver/agentframework/_version.py
azure/ai/agentserver/agentframework/agent_framework.py
azure/ai/agentserver/agentframework/py.typed
azure/ai/agentserver/agentframework/tool_client.py
azure/ai/agentserver/agentframework/models/__init__.py
azure/ai/agentserver/agentframework/models/agent_framework_input_converters.py
azure/ai/agentserver/agentframework/models/agent_framework_output_non_streaming_converter.py
azure/ai/agentserver/agentframework/models/agent_framework_output_streaming_converter.py
azure/ai/agentserver/agentframework/models/agent_id_generator.py
azure/ai/agentserver/agentframework/models/constants.py
azure/ai/agentserver/agentframework/models/utils/__init__.py
azure/ai/agentserver/agentframework/models/utils/async_iter.py
azure_ai_agentserver_agentframework-1.0.0b7.dist-info/licenses/LICENSE
azure_ai_agentserver_agentframework-1.0.0b7.dist-info/METADATA
azure_ai_agentserver_agentframework-1.0.0b7.dist-info/WHEEL
azure_ai_agentserver_agentframework-1.0.0b7.dist-info/top_level.txt
azure_ai_agentserver_agentframework-1.0.0b7.dist-info/RECORD
