Metadata-Version: 2.4
Name: azure-ai-agentserver-agentframework
Version: 1.0.0b7
Summary: Agents server adapter for Azure AI
Author-email: Microsoft Corporation <azpysdkhelp@microsoft.com>
License-Expression: MIT
Project-URL: repository, https://github.com/Azure/azure-sdk-for-python
Keywords: azure,azure sdk
Classifier: Programming Language :: Python
Classifier: Programming Language :: Python :: 3 :: Only
Classifier: Programming Language :: Python :: 3
Classifier: Programming Language :: Python :: 3.10
Classifier: Programming Language :: Python :: 3.11
Classifier: Programming Language :: Python :: 3.12
Classifier: Programming Language :: Python :: 3.13
Requires-Python: >=3.10
License-File: LICENSE
Requires-Dist: azure-ai-agentserver-core>=1.0.0b7
Requires-Dist: agent-framework-azure-ai>=1.0.0b251112
Requires-Dist: agent-framework-core>=1.0.0b251112
Requires-Dist: opentelemetry-exporter-otlp-proto-grpc>=1.36.0
Dynamic: license-file
